 [
    {
      "id": 1,
      "name": "David Kim",
      "lastContact": 6 ,
      "goalDays" : 30,
      "tags": ["WORK"],
      "status": "Almost Due",
      "bio":"A dedicated professional who values consistency and staying connected with colleagues.",
      "email": "david.kim@gmail.com" ,
      "image": "https://i.ibb.co.com/Z36cPMD/female-5.avif"
    },
    {
      "id": 2,
      "name": "Emma Wilson",
      "lastContact": 16,
      "goalDays" : 30,
      "tags": ["FAMILY","TRAVEL"],
      "status": "Overdue",
      "bio":"A caring family member who always keeps loved ones close and connected.",
      "email": "emma.wilson@gmail.com",
      "image": "https://i.ibb.co.com/SX4VWm9s/female-4.avif"
    },
    {
      "id": 3,
      "name": "Lisa Nakamura",
      "lastContact": 8,
      "goalDays" : 30,
      "tags": ["WORK"],
      "status": "Overdue",
      "bio":"Focused and hardworking, always striving to maintain strong work relationships.",
      "email": "lisa.nakamura@gmail.com",
      "image": "https://i.ibb.co.com/BKzSM2SM/female-3.webp"
    },
    {
      "id": 4,
      "name": "James Wright",
      "lastContact": 14,
      "goalDays" : 30,
      "tags": ["HOBBY", "TRAVEL"],
      "status": "Overdue",
      "bio":"An adventurous soul who loves exploring new places and sharing experiences.",
      "email": "james.wright@gmail.com",
      "image": "https://i.ibb.co.com/0b9MS3q/female-2.webp"
    },
    {
      "id": 5,
      "name": "Sophia Lee",
      "lastContact": 3,
      "goalDays" : 30,
      "tags": ["WORK"],
      "status": "On Track",
      "bio":"Organized and proactive, always on top of her work and connections.",
      "email": "sophia.lee@gmail.com" ,
      "image": "https://i.ibb.co.com/DH38Jvxp/female-1.jpg"
    },
    {
      "id": 6,
      "name": "Michael Brown",
      "lastContact": 10,
      "goalDays" : 30,
      "tags": ["FAMILY","FRIEND"],
      "status": "Overdue",
      "bio":"Family-oriented and dependable, values meaningful conversations.",
      "email": "michael.brown@gmail.com",
      "image": "https://i.ibb.co.com/1fjtYqdW/f-14.jpg"
    },
    {
      "id": 7,
      "name": "Olivia Davis",
      "lastContact": 2,
      "goalDays" : 30,
      "tags": ["FRIEND"],
      "status": "On Track",
      "bio":"Passionate about travel and discovering new cultures around the world.",
      "email": "olivia.davis@gmail.com",
      "image": "https://i.ibb.co.com/6cq8cpdh/f-13.jpg"
    },
    {
      "id": 8,
      "name": "William Johnson",
      "lastContact": 7,
      "goalDays" : 30,
      "tags": ["TRAVEL","FRIEND"],
      "status": "Almost Due",
      "bio":"A friendly and social person who enjoys staying in touch with close friends.",
      "email": "william.johnson@gmail.com",
      "image": "https://i.ibb.co.com/wNXcxCJk/f-12.jpg"
    },
    {
      "id": 9,
      "name": "Ava Martinez",
      "lastContact": 1,
      "goalDays" : 30,
      "tags": ["HOBBY"],
      "status": "On Track",
      "bio":"Creative and fun-loving, enjoys hobbies and expressing herself.",
      "email": "ava.martinez@gmail.com",
      "image": "https://i.ibb.co.com/3mLcYH9d/f-11.jpg"
    },
    {
      "id": 10,
      "name": "Ethan Anderson",
      "lastContact": 12,
      "goalDays" : 30,
      "tags": ["WORK"],
      "status": "Overdue",
      "bio":"Work-focused and driven, but sometimes loses track of connections.",
      "email": "ethan.anderson@gmail.com",
      "image": "https://i.ibb.co.com/dsBw5k8z/f-10.jpg"
    },
    {
      "id": 11,
      "name": "Mia Thompson",
      "lastContact": 4,
      "goalDays" : 30,
      "tags": ["FAMILY","FRIEND"],
      "status": "Almost Due",
      "bio":"Warm and supportive, always there for her family when needed.",
      "email": "mia.thompson@gmail.com" ,
      "image": "https://i.ibb.co.com/4RZjGWs0/f-9.webp"
    },
    {
      "id": 12,
      "name": "Noah Garcia",
      "lastContact": 9,
      "goalDays" : 30,
      "tags": ["FRIEND"],
      "status": "Overdue",
      "bio":"A loyal friend who values deep and meaningful friendships.",
      "email": "noah.garcia@gmail.com" ,
      "image": "https://i.ibb.co.com/PZpkwkkF/f-8.jpg"
    },
    {
      "id": 13,
      "name": "Isabella Rodriguez",
      "lastContact": 2,
      "goalDays" : 30,
      "tags": ["TRAVEL"],
      "status": "On Track",
      "bio":"Loves traveling and building connections across different places.",
      "email": "isabella.rodriguez@gmail.com" ,
      "image": "https://i.ibb.co.com/fGSCzD5S/f-7.jpg"
    },
    {
      "id": 14,
      "name": "Liam Wilson",
      "lastContact": 5,
      "goalDays" : 30,
      "tags": ["WORK"],
      "status": "Almost Due",
      "bio":"A balanced professional who manages work and relationships well.",
      "email": "liam.wilson@gmail.com",
      "image": "https://i.ibb.co.com/ksXh7Z4h/f-6.webp"
    }
  ]
